chiselai/__init__.py
chiselai/core.py
chiselai-0.1.0.1.dist-info/LICENSE
chiselai-0.1.0.1.dist-info/METADATA
chiselai-0.1.0.1.dist-info/WHEEL
chiselai-0.1.0.1.dist-info/RECORD
